ssl_expiry_monitor/__init__.py
ssl_expiry_monitor-0.1.0.dist-info/LICENSE
ssl_expiry_monitor-0.1.0.dist-info/METADATA
ssl_expiry_monitor-0.1.0.dist-info/WHEEL
ssl_expiry_monitor-0.1.0.dist-info/RECORD
